<?xml version="1.0" encoding="utf-8" ?>
<dwsync>
<file name="favicon.ico" server="C:/Users/Soheil/Documents/Telecommit/" local="130463321240000000" remote="130463321240000000" Dst="2" />
<file name="apple-touch-icon-144-precomposed.png" server="C:/Users/Soheil/Documents/Telecommit/" local="130463321240000000" remote="130463321240000000" Dst="2" />
<file name="apple-touch-icon-114-precomposed.png" server="C:/Users/Soheil/Documents/Telecommit/" local="130463321240000000" remote="130463321240000000" Dst="2" />
<file name="apple-touch-icon-72-precomposed.png" server="C:/Users/Soheil/Documents/Telecommit/" local="130463321240000000" remote="130463321240000000" Dst="2" />
<file name="apple-touch-icon-57-precomposed.png" server="C:/Users/Soheil/Documents/Telecommit/" local="130463321240000000" remote="130463321240000000" Dst="2" />
<file name="favicon.ico" server="C:/xampp/htdocs/Telecommit/" local="130463321240000000" remote="130463321240000000" Dst="2" />
<file name="apple-touch-icon-144-precomposed.png" server="C:/xampp/htdocs/Telecommit/" local="130463321240000000" remote="130463321240000000" Dst="2" />
<file name="apple-touch-icon-114-precomposed.png" server="C:/xampp/htdocs/Telecommit/" local="130463321240000000" remote="130463321240000000" Dst="2" />
<file name="apple-touch-icon-72-precomposed.png" server="C:/xampp/htdocs/Telecommit/" local="130463321240000000" remote="130463321240000000" Dst="2" />
<file name="apple-touch-icon-57-precomposed.png" server="C:/xampp/htdocs/Telecommit/" local="130463321240000000" remote="130463321240000000" Dst="2" />
<file name="favicon.ico" server="C:/wamp/www/Telecommit" local="130463321240000000" remote="130463321240000000" Dst="2" />
<file name="apple-touch-icon-144-precomposed.png" server="C:/wamp/www/Telecommit" local="130463321240000000" remote="130463321240000000" Dst="2" />
<file name="apple-touch-icon-114-precomposed.png" server="C:/wamp/www/Telecommit" local="130463321240000000" remote="130463321240000000" Dst="2" />
<file name="apple-touch-icon-72-precomposed.png" server="C:/wamp/www/Telecommit" local="130463321240000000" remote="130463321240000000" Dst="2" />
<file name="apple-touch-icon-57-precomposed.png" server="C:/wamp/www/Telecommit" local="130463321240000000" remote="130463321240000000" Dst="2" />
<file name="apple-touch-icon-114-precomposed.png" server="C:/wamp/www/Telecommit/" local="130463321240000000" remote="130463321240000000" Dst="2" />
<file name="apple-touch-icon-144-precomposed.png" server="C:/wamp/www/Telecommit/" local="130463321240000000" remote="130463321240000000" Dst="2" />
<file name="apple-touch-icon-57-precomposed.png" server="C:/wamp/www/Telecommit/" local="130463321240000000" remote="130463321240000000" Dst="2" />
<file name="apple-touch-icon-72-precomposed.png" server="C:/wamp/www/Telecommit/" local="130463321240000000" remote="130463321240000000" Dst="2" />
<file name="favicon.ico" server="C:/wamp/www/Telecommit/" local="130463321240000000" remote="130463321240000000" Dst="2" />
</dwsync>